CHANGES.txt
LICENSE
README.txt
bootstrap.py
buildout.cfg
setup.cfg
setup.py
iw/__init__.py
iw.email.egg-info/PKG-INFO
iw.email.egg-info/SOURCES.txt
iw.email.egg-info/dependency_links.txt
iw.email.egg-info/entry_points.txt
iw.email.egg-info/namespace_packages.txt
iw.email.egg-info/not-zip-safe
iw.email.egg-info/requires.txt
iw.email.egg-info/top_level.txt
iw/email/README.txt
iw/email/__init__.py
iw/email/cheetah_template.py
iw/email/configure.zcml
iw/email/interfaces.py
iw/email/mail.py
iw/email/mako_template.py
iw/email/templates.py
iw/email/testing.py
iw/email/utils.py
iw/email/docs/README.txt
iw/email/docs/testing.txt
iw/email/doctests/README.txt
iw/email/doctests/template.txt
iw/email/tests/__init__.py
iw/email/tests/bullet.gif
iw/email/tests/mail.mak
iw/email/tests/mail.tmpl
iw/email/tests/test_emaildocs.py
iw/email/tests/test_emaildocstrings.py