Metadata-Version: 1.0
Name: iw.email
Version: 1.3
Summary: Email utilities
Home-page: UNKNOWN
Author: Ingeniweb
Author-email: support@ingeniweb.com
License: GPL
Platform: UNKNOWN
Classifier: Programming Language :: Python
Classifier: Topic :: Software Development :: Libraries :: Python Modules
